django_sandstorm/__init__.py
django_sandstorm/context.py
django_sandstorm/middleware.py
django_sandstorm-0.0.2.dist-info/DESCRIPTION.rst
django_sandstorm-0.0.2.dist-info/METADATA
django_sandstorm-0.0.2.dist-info/RECORD
django_sandstorm-0.0.2.dist-info/WHEEL
django_sandstorm-0.0.2.dist-info/metadata.json
django_sandstorm-0.0.2.dist-info/top_level.txt
