Metadata-Version: 1.1
Name: django-sandstorm
Version: 0.0.2
Summary: A sandstorm.io integration for Django.
Home-page: https://github.com/phildini/django-sandstorm
Author: Philip James
Author-email: pjj@philipjohnjames.com
License: MIT License
Platform: UNKNOWN
Classifier: Environment :: Web Environment
Classifier: Framework :: Django
Classifier: Intended Audience :: Developers
Classifier: License :: OSI Approved :: MIT License
Classifier: Operating System :: OS Independent
Classifier: Programming Language :: Python
Classifier: Programming Language :: Python :: 3
Classifier: Programming Language :: Python :: 3.2
Classifier: Programming Language :: Python :: 3.3
Classifier: Topic :: Internet :: WWW/HTTP
